seasave_measurement/Dship.py
seasave_measurement/__init__.py
seasave_measurement/instrument_config.py
seasave_measurement/server_test.py
seasave_measurement-0.0.1.dist-info/LICENSE
seasave_measurement-0.0.1.dist-info/WHEEL
seasave_measurement-0.0.1.dist-info/METADATA
seasave_measurement-0.0.1.dist-info/RECORD
