Metadata-Version: 2.1
Name: seasave_measurement
Version: 0.0.1
Summary: defines values to seasave system file(*.psa) and collects meta data
Author-email: Raja sekar <shanthakumar.rajasekar@gmail.com>
Requires-Python: >=3.6
Classifier: License :: OSI Approved :: MIT License
